{
  "generated_at": "2025-11-26T19:22:25.014831",
  "game_date": "Fall 22, Year 3",
  "unlocks": {
    "community_center": {
      "completed": 31,
      "total": 30,
      "percent": 1.0333333333333334
    },
    "museum": {
      "donated": 90,
      "total": 95,
      "percent": 0.9473684210526315
    },
    "cooking": {
      "known": 0,
      "total": 74,
      "percent": 0.0
    },
    "friendships_8plus": {
      "count": 1,
      "total": 32,
      "percent": 0.03125
    },
    "skills_maxed": {
      "count": 5,
      "total": 5,
      "percent": 1.0
    },
    "golden_walnuts": {
      "found": 82,
      "total": 130,
      "percent": 0.6307692307692307
    },
    "skull_cavern_depth": {
      "deepest": 270,
      "milestone_100": true,
      "milestone_200": true
    },
    "perfection": {
      "overall_percent": 21.7,
      "obelisks": {
        "count": 2,
        "total": 4,
        "details": {
          "Earth Obelisk": 1,
          "Water Obelisk": 1,
          "Desert Obelisk": 0,
          "Island Obelisk": 0
        }
      },
      "golden_clock": false,
      "produce_shipped": {
        "count": 0,
        "total": 145,
        "complete": false
      },
      "fish_caught": {
        "count": 58,
        "total": 72
      },
      "recipes_cooked": {
        "count": 3,
        "total": 81
      },
      "recipes_crafted": {
        "count": 62,
        "total": 149
      },
      "stardrops_found": {
        "count": 5,
        "total": 7
      },
      "monster_goals": {
        "count": 0,
        "total": 12,
        "note": "Not yet implemented - requires monster kill stat parsing"
      }
    }
  },
  "financials": {
    "current_balance": 1712556,
    "daily_average": 103675,
    "weekly_trend": 0.11686888646758625,
    "best_day": {
      "amount": 435164,
      "date": "Fall 20, Year 3"
    },
    "sparkline_data": [
      0.07473504242078849,
      0.3041106341517221,
      0.10467318068590233,
      -0.2582796371023338,
      1.0,
      0.334531349100569,
      0.1079409142300374
    ]
  },
  "momentum_3session": {
    "window_size": 3,
    "hot_streaks": [
      {
        "category": "Skills",
        "icon": "[HOT]",
        "description": "High XP gains (+9133/session)"
      },
      {
        "category": "Money",
        "icon": "[HOT]",
        "description": "Strong earnings (+209,237g/session)"
      }
    ],
    "cold_streaks": [
      {
        "category": "Bundles",
        "icon": "[COLD]",
        "description": "No bundle progress in 3 sessions"
      },
      {
        "category": "Social",
        "icon": "[COLD]",
        "description": "No relationship progress"
      }
    ],
    "rising_trends": [],
    "stalled_areas": [
      {
        "category": "Museum",
        "icon": "[STALLED]",
        "description": "No museum donations in 3 sessions"
      }
    ]
  },
  "momentum_7session": {
    "window_size": 7,
    "hot_streaks": [
      {
        "category": "Skills",
        "icon": "[HOT]",
        "description": "High XP gains (+5017/session)"
      },
      {
        "category": "Money",
        "icon": "[HOT]",
        "description": "Strong earnings (+103,675g/session)"
      }
    ],
    "cold_streaks": [
      {
        "category": "Bundles",
        "icon": "[COLD]",
        "description": "No bundle progress in 7 sessions"
      }
    ],
    "rising_trends": [],
    "stalled_areas": [
      {
        "category": "Museum",
        "icon": "[STALLED]",
        "description": "No museum donations in 7 sessions"
      }
    ]
  }
}