{
  "selected_at": "2025-11-28T12:00:00Z",
  "reasoning": "Selected based on: (1) Near-completion - Museum at 94% (5 items to Stardrop!); (2) goals.md explicit Fall Year 3 priorities - Secret Woods and Professor Snail; (3) Dependency chain - Prof Snail unlocks Field Office for fossils; (4) Casino for endgame content; (5) Leo friendship for town expansion. Note: Golden Walnuts now COMPLETE (130/130)!",
  "unlocks": [
    {
      "name": "Museum Collection (95)",
      "completion_percent": 94,
      "next_step": "Donate all 95 items to Museum (90/95)",
      "category": "Progression"
    },
    {
      "name": "Secret Woods",
      "completion_percent": 0,
      "next_step": "Upgrade Axe to Steel or better",
      "category": "Map Access"
    },
    {
      "name": "Professor Snail's Tent",
      "completion_percent": 0,
      "next_step": "Free Professor Snail from boulder",
      "category": "Island Features"
    },
    {
      "name": "Casino (Club Card)",
      "completion_percent": 0,
      "next_step": "Complete 'Mysterious Qi' questline",
      "category": "Progression"
    },
    {
      "name": "Leo's Return to Town",
      "completion_percent": 0,
      "next_step": "Befriend Leo (6+ hearts)",
      "category": "Progression"
    }
  ]
}
