{
  "selected_at": "2025-11-22T09:30:00",
  "reasoning": "Selected based on obelisk building momentum (just built 1 obelisk, 1.7% perfection gain), goals.md priorities for remaining 3 obelisks, and strategic progression. Mixed near-completion (Museum 87%, Golden Walnuts 59%) with critical easy wins (Beach Bridge, Secret Woods) and Island unlocks (Professor Snail blocks Field Office).",
  "unlocks": [
    {
      "name": "Museum Collection (95)",
      "completion_percent": 87,
      "next_step": "Donate all 95 items to Museum (83/95)",
      "category": "Progression"
    },
    {
      "name": "Golden Walnuts (100)",
      "completion_percent": 59,
      "next_step": "Find 100 Golden Walnuts (59/100)",
      "category": "Island Features"
    },
    {
      "name": "Professor Snail's Tent",
      "completion_percent": 0,
      "next_step": "Free Professor Snail from boulder",
      "category": "Island Features"
    },
    {
      "name": "Beach Bridge",
      "completion_percent": 0,
      "next_step": "Collect 300 wood",
      "category": "Map Access"
    },
    {
      "name": "Secret Woods",
      "completion_percent": 0,
      "next_step": "Upgrade Axe to Steel or better",
      "category": "Map Access"
    }
  ]
}